pyPSQC/__init__.py
pyPSQC/feature_extraction.py
pyPSQC/model_coef.json
pyPSQC/prepare_data.py
pyPSQC/psqc.py
pyPSQC/quality_prediction.py
pyPSQC/utils.py
pyPSQC-1.0.0.dist-info/LICENSE
pyPSQC-1.0.0.dist-info/METADATA
pyPSQC-1.0.0.dist-info/WHEEL
pyPSQC-1.0.0.dist-info/top_level.txt
pyPSQC-1.0.0.dist-info/RECORD
