Metadata-Version: 2.1
Name: pyPSQC
Version: 1.0.0
Summary: Python pakage for the quality control system for automated prostate segmentation on T2-weighted MRI.
Home-page: https://github.com/MohammedSunoqrot/pyPSQC
Author: Mohammed R. S. Sunoqrot
Author-email: mohammed.sunoqrot@ntnu.no
Project-URL: Bug Tracker, https://github.com/MohammedSunoqrot/pyPSQC/issues
Classifier: Programming Language :: Python :: 3
Classifier: Programming Language :: Python :: 3.8
Classifier: Programming Language :: Python :: 3.9
Classifier: Programming Language :: Python :: 3.10
Classifier: Programming Language :: Python :: 3.11
Classifier: License :: OSI Approved :: MIT License
Classifier: Operating System :: OS Independent
Requires-Python: >=3.8
License-File: LICENSE
Requires-Dist: numpy
Requires-Dist: pyAutoRef
Requires-Dist: pyradiomics ==3.0.1
